odoo/addons/l10n_ir_hr_contract/README.rst
odoo/addons/l10n_ir_hr_contract/__init__.py
odoo/addons/l10n_ir_hr_contract/__manifest__.py
odoo/addons/l10n_ir_hr_contract/i18n/fa.po
odoo/addons/l10n_ir_hr_contract/i18n/l10n_ir_hr_contract.pot
odoo/addons/l10n_ir_hr_contract/models/__init__.py
odoo/addons/l10n_ir_hr_contract/models/hr_contract.py
odoo/addons/l10n_ir_hr_contract/readme/CONFIGURE.rst
odoo/addons/l10n_ir_hr_contract/readme/CONTRIBUTORS.rst
odoo/addons/l10n_ir_hr_contract/readme/DESCRIPTION.rst
odoo/addons/l10n_ir_hr_contract/readme/USAGE.rst
odoo/addons/l10n_ir_hr_contract/static/description/icon.png
odoo/addons/l10n_ir_hr_contract/static/description/index.html
odoo/addons/l10n_ir_hr_contract/views/hr_contract_view.xml
odoo14_addon_l10n_ir_hr_contract-14.0.3.0.1.dev10.dist-info/METADATA
odoo14_addon_l10n_ir_hr_contract-14.0.3.0.1.dev10.dist-info/WHEEL
odoo14_addon_l10n_ir_hr_contract-14.0.3.0.1.dev10.dist-info/top_level.txt
odoo14_addon_l10n_ir_hr_contract-14.0.3.0.1.dev10.dist-info/RECORD
